Metadata-Version: 2.1
Name: simplelayout-zweien
Version: 0.0.5
Summary: A sample Python project
Home-page: UNKNOWN
Author-email: 278954153@qq.com
License: UNKNOWN
Project-URL: Bug Reports, https://github.com/pypa/sampleproject/issues
Project-URL: Funding, https://donate.pypi.org
Project-URL: Say Thanks!, http://saythanks.io/to/example
Project-URL: Source, https://github.com/pypa/sampleproject/
Platform: UNKNOWN
Requires-Python: >=3.6, <4
Requires-Dist: numpy
Requires-Dist: matplotlib
Requires-Dist: scipy
Provides-Extra: dev
Requires-Dist: check-manifest ; extra == 'dev'
Provides-Extra: test
Requires-Dist: coverage ; extra == 'test'
